{"cameraMode":{"drawMode":0,"name":"Shaded","section":"Shading Mode"},"sceneLighting":false,"audioPlay":false,"sceneViewState":{"m_AlwaysRefresh":false,"showFog":true,"showSkybox":false,"showFlares":true,"showImageEffects":true,"showParticleSystems":true,"showVisualEffectGraphs":true,"m_FxEnabled":true},"in2DMode":false,"pivot":{"x":0.0,"y":6.050000190734863,"z":9.5367431640625e-7},"rotation":{"x":-0.411515474319458,"y":0.45394715666770937,"z":-0.24865283071994782,"w":-0.7508075833320618},"size":6.558391571044922,"orthographic":false}